<?xml version="1.0"?>
<!DOCTYPE webpage
  PUBLIC "-//Norman Walsh//DTD Website V2.2//EN"
         "http://docbook.sourceforge.net/release/website/2.2/website.dtd" [
]>

<webpage id="mobile-logos">
<config param="desc" value="NetBSD Mobile Logos"/>
<config param="cvstag" value="$NetBSD: mobile-logos.xml,v 1.1 2004/10/31 14:35:31 jschauma Exp $"/>
<config param="rcsdate" value="$Date: 2004/10/31 14:35:31 $"/>
<head>
<title>NetBSD Logos for your mobile phone, backgrounds etc.</title>
</head>

<sect1>

<sect2 id="mobile">
<title>Logos for your mobile phone</title>

<para>
The following images are in Nokia LogoManager format, suitable for mobile
phones:
</para>

<sect3>
<title>From Dawid Szyma&ntilde;ski &lt;dawszy@arhea.net&gt;</title>
    

    <ulink url="../images/logos/dawsy/NetBSDoper.nol">
    <imagedata border="0" fileref="../images/logos/dawsy/NetBSDoper.gif"
     width="72" height="14" alt="[NetBSD button]"/></ulink>
    &nbsp;

    <ulink url="../images/logos/dawsy/evil1.nlm">
    <imagedata border="0" fileref="../images/logos/dawsy/evil1.gif"
     width="84" height="48" alt="[NetBSD button]"/></ulink>
    &nbsp;

    <ulink url="../images/logos/dawsy/evil2.nlm">
    <imagedata border="0" fileref="../images/logos/dawsy/evil2.gif"
     width="84" height="48" alt="[NetBSD button]"/></ulink>
    &nbsp;

    <ulink url="../images/logos/dawsy/justevil.nlm">
    <imagedata border="0" fileref="../images/logos/dawsy/justevil.gif"
     width="84" height="48" alt="[NetBSD button]"/></ulink>

<para>
The following logo is in Nokia Data Suite format. Alternatively, if you want
to draw the picture yourself, you can look at the
<ulink url="../images/logos/ssala/darby-l.jpg">pixelized version</ulink>
for help.
</para>
</sect3>

<sect3>
<title>From Sebastian Sala &lt;sebastian.sala@hut.fi&gt;</title>
    

    <ulink url="../images/logos/ssala/darby.gms">
    <imagedata border="0" fileref="../images/logos/ssala/darby.jpg"
     width="72" height="14" alt="[NetBSD button]"/></ulink>
</sect3>

<sect3>
<title>Zwahlendesign</title>
<ulink
url="http://www.zwahlendesign.ch/en/16t6xx.html#bsd">Zwahlendesign</ulink>
offers some BSD themes for various cell phones.
</sect3>

<sect3 id="wallpapers">
<title>>Wallpapers for your desktop</title>
<sect4>
<title>From Jan Schaumann &lt;jschauma@NetBSD.org&gt;</title>
    

  <ulink
url="ftp://ftp.NetBSD.org/pub/NetBSD/misc/jschauma/background.jpg.bz2"><imagedata
  border="0" fileref="../images/logos/jschauma/background-small.jpg" width="120"
   height="96" alt="Desktop Background" vspace="5"/></ulink>
</sect4>

<sect4>
<title>From Karsten Kruse &lt;tecneeq@tecneeq.de&gt;</title>
    

  <ulink url="../images/logos/tecneeq-wp.png"><imagedata border="0"
fileref="../images/logos/tecneeq-wp-small.png" width="128" height="96"
alt="Desktop Background NetBSD/Brain" vspace="5"/></ulink>
</sect4>

<sect4>
<title>From Turea Alexandru Teodor &lt;classicmanpro at yahoo com&gt;</title>
    

  <ulink url="../images/logos/NetBSD-world.jpg">
    <imagedata border="0" fileref="../images/logos/NetBSD-world-small.jpg" width="128"
    height="96" alt="NORAD-like computer screen with world map" vspace="5"/></ulink>

  <ulink url="../images/logos/NetBSD-hardware.jpg">
    <imagedata border="0" fileref="../images/logos/NetBSD-hardware-small.jpg" width="128"
    height="96" alt="A NetBSD daemon running on high-tech hardware"  vspace="5"/></ulink> 
</sect4>
</sect3>

<sect3 id="skins">
<title>XMMS Skins</title>

  <ulink url="http://www.tecneeq.de/files/themes/NetBSD-xmms-skin.tgz"><imagedata border="0"
fileref="../images/logos/tecneeq-skin.png" width="168" height="252"
alt="NetBSD XMMS Skin" vspace="5"/></ulink>
</sect3>
</sect2>

</sect1>

</webpage>
