<?xml version="1.0"?>
<!DOCTYPE webpage
  PUBLIC "-//NetBSD//DTD Website-based NetBSD Extension//EN"
	 "http://www.NetBSD.org/XML/htdocs/lang/share/xml/website-netbsd.dtd">

<webpage id="Hardware-eisa">
<config param="desc" value="The NetBSD Foundation"/>
<config param="cvstag" value="$NetBSD: eisa.xml,v 1.7 2006/02/12 13:38:58 hubertf Exp $"/>
<config param="rcsdate" value="$Date: 2006/02/12 13:38:58 $"/>
<head>
<title>EISA Hardware Supported by NetBSD</title>
</head>

<sect1 id="top">
<title>Machine-independent EISA drivers</title>

<para>
The following devices (<emphasis>driver name in parentheses</emphasis>) are supported by
machine-independent EISA drivers.  If you do not see your device listed here,
check your platform's page; there may not yet be a machine-independent driver
for your device.
</para>

<para>
Alternatively, it may be the case that your device is compatible with one
listed here, or your device may not be listed due to an oversight.  If you
are unsure, please boot a -current kernel or send mail to
<email>netbsd-help@NetBSD.org</email>.
</para>

<para>
Please note that these pages reflect the state of NetBSD-current. To check
the supported hardware list for a specific release of NetBSD, check
that release's installation notes.
</para>

<sect2 id="eisa-devices">
<title>Supported EISA devices</title>

<itemizedlist>
    <listitem> SCSI and RAID host adapters (<ulink url="scsipi.html">click here</ulink> for a list
    of supported SCSI target devices)	 
    <itemizedlist>
	<listitem> Adaptec 174x (&man.ahb.4;)</listitem>
	<listitem> Adaptec AIC-7770 and AHA-274x (&man.ahc.4;)</listitem>
	<listitem> BusLogic 74x (&man.bha.4;)</listitem>
	<listitem> Compaq IDA, IDA-2, IEAS, SMART, SMART-2/E (&man.cac.4;)</listitem>
	<listitem> DPT SmartRAID III/IV and DPT SmartCache III/IV (&man.dpt.4;)</listitem>
	<listitem> Mylex DAC960, DEC SWXCR-EA and SWXCR-EB (&man.mlx.4;)</listitem>
	<listitem> Ultrastor 24f (&man.uha.4;)</listitem>
    </itemizedlist>
    </listitem>
    <listitem> Network interfaces
    <itemizedlist>
	<listitem> 3Com 3c579 (&man.ep.4;). <emphasis>Note: this driver also supports
	           3c509 ISA cards that masquerade as EISA devices.</emphasis></listitem>
	<listitem> Digital DEFEA SAS and DAS FDDI cards (&man.fea.4;)</listitem>	    
	<listitem> Digital DE422 Ethernet interfaces (&man.le.4;)</listitem>	    
	<listitem> Digital DE425 Ethernet interfaces (&man.tlp.4;)</listitem>	    
    </itemizedlist>
    </listitem>	    
</itemizedlist>
</sect2>

</sect1>

<parentsec url="./" text="Hardware Devices Supported by NetBSD"/>
</webpage>
