<?xml version="1.0" encoding="UTF-8"?>
<!DOCTYPE webpage
 PUBLIC "-//NetBSD//DTD Website-based NetBSD Extension//EN"
        "http://www.NetBSD.org/XML/htdocs/lang/share/xml/website-netbsd.dtd">

<webpage id="ja-ports-acorn32-history">
<config param="desc" value="NetBSD/acorn32 の歴史"/>
<config param="cvstag" value="$NetBSD: history.xml,v 1.1 2007/06/09 13:31:45 dsieger Exp $"/>
<!-- Based on english version: -->
<!-- NetBSD: history.xml,v 1.1 2007/06/09 13:31:45 dsieger Exp   -->
<config param="rcsdate" value="$Date: 2007/06/09 13:31:45 $"/>
<head>

<!-- Copyright (c) 1996-2007
	The NetBSD Foundation, Inc.  ALL RIGHTS RESERVED. -->

<title>NetBSD/acorn32 の歴史</title>
</head>

<sect1 id="acorn32_history">

  <para>
    NetBSD/acorn32 は、 NetBSD/arm32 ポートから分割されたものです。これは、
    arm32 ポートが成長し、維持するには多様すぎる機種が含まれるように
    なったためです。
  </para>

  <para>
    NetBSD/arm32 は、もともと <quote>RiscBSD</quote> と呼ばれるプロジェクトの
    基本部分を構成するものでした。 RiscBSD グループ (もとは、 Mark Brinicombe、
    Robert Black、 Neil Carson、 Manar Hussain、 Scott Stevens、
    Melvin Tang-Richardson) は、 Acorn が新たに発表した ARM610 プロセッサーベースの
    RiscPC システムへ、フリー unix オペレーティングシステムを移植したいと
    考えていました。 RiscBSD プロジェクトは、 Acorn の RiscPC 発売時に、
    <ulink url="http://www.xara.co.uk/">Xara</ulink> の <ulink
    url="http://www.thermal.demon.co.uk/">Gordon Taylor</ulink>
    の参加のおかげで、はじめて形になりました。それから、 Mach、 Linux、
    FreeBSD などを慎重に研究したのち、私たちは OS として NetBSD を選びました。
  </para>

  <para>
    時間が経つにつれ、このチームは縮小し、 Mark、 Neil、 Robert、 Scott
    が残るだけになりました。その後、 Network Computer (現 <ulink
    url="http://www.liberate.com/">Liberate Technologies</ulink>)
    は、 <ulink
    url="http://www.research.compaq.com/SRC/iag/">Digital
    Shark</ulink> コンピューター (<ulink
    url="../shark/">NetBSD/shark</ulink> 参照)
    上での使用のために、オペレーティングシステムおよび関連
    toolchain のさまざまな拡張に出資しました。
  </para>
</sect1>

<parentsec url="./" text="&os;/acorn32 ポートのページ"/>

</webpage>
